yta_video_advanced/__init__.py
yta_video_advanced/scenes.py
yta_video_advanced-0.0.1.dist-info/LICENSE
yta_video_advanced-0.0.1.dist-info/METADATA
yta_video_advanced-0.0.1.dist-info/WHEEL
yta_video_advanced-0.0.1.dist-info/RECORD
